zana_ai/__init__.py
zana_ai/phind.py
zana_ai-0.1.dist-info/METADATA
zana_ai-0.1.dist-info/WHEEL
zana_ai-0.1.dist-info/entry_points.txt
zana_ai-0.1.dist-info/top_level.txt
zana_ai-0.1.dist-info/RECORD
